{
  "e893bb34-dd97-4bab-a6af-c3c480e9dbe0": {
    "status": "error",
    "message": "Unexpected Response: 400 (Bad Request)\nRaw response content:\nb'{\"status\":{\"error\":\"Format error in JSON body: value c20c1569-35e0-4b04-9a13-b5b7b0ea16ec_0 is not a valid point ID, valid values are either an unsigned integer or a UUID\"},\"time\":0.0}'"
  },
  "232efd91-5a15-44f9-b3b8-2573b01a7837": {
    "status": "error",
    "message": "Unexpected Response: 400 (Bad Request)\nRaw response content:\nb'{\"status\":{\"error\":\"Format error in JSON body: value 650e900e-80d2-44ca-bf00-da8d688faad3_0 is not a valid point ID, valid values are either an unsigned integer or a UUID\"},\"time\":0.0}'"
  },
  "1f252003-6264-471d-b17f-55d265ab1188": {
    "status": "error",
    "message": "Unexpected Response: 400 (Bad Request)\nRaw response content:\nb'{\"status\":{\"error\":\"Format error in JSON body: value f77d01b7-93f6-4fd0-8315-dbef35e35814_0 is not a valid point ID, valid values are either an unsigned integer or a UUID\"},\"time\":0.0}'"
  },
  "7b5bb4fe-caed-4b21-a25a-ff82a03f2399": {
    "status": "error",
    "stage": "split",
    "title": "constitution_of_india.pdf",
    "total_chunks": 690,
    "ingested": 0,
    "percent": 0,
    "started_at": 1762168732.7171493,
    "updated_at": 1762168766.5208964,
    "eta_seconds": null,
    "message": "Unexpected Response: 400 (Bad Request)\nRaw response content:\nb'{\"status\":{\"error\":\"Format error in JSON body: value 34b18721-b681-48e1-b8ff-83639a1c607b_0 is not a valid point ID, valid values are either an unsigned integer or a UUID\"},\"time\":0.0}'"
  },
  "a97bac3a-9b49-4808-968f-0daba2536cb8": {
    "status": "ready",
    "stage": "done",
    "title": "250883_english_01042024.pdf",
    "total_chunks": 356,
    "ingested": 356,
    "percent": 100,
    "started_at": 1762202946.7489703,
    "updated_at": 1762203225.8783953,
    "eta_seconds": 0
  },
  "30e0c693-fb8e-4adb-aa02-6cd8ca95cb7e": {
    "status": "ready",
    "stage": "done",
    "title": "mock_fir_constitution_itact.pdf",
    "total_chunks": 5,
    "ingested": 5,
    "percent": 100,
    "started_at": 1762203382.1035883,
    "updated_at": 1762203384.6386867,
    "eta_seconds": 0
  },
  "162f1628-ff89-4306-839f-4bdee0df68ee": {
    "status": "ready",
    "stage": "done",
    "title": "mock_fir_constitution_itact.pdf",
    "total_chunks": 5,
    "ingested": 5,
    "percent": 100,
    "started_at": 1762203625.968459,
    "updated_at": 1762203628.319116,
    "eta_seconds": 0
  },
  "d2d76e6a-6049-4c6b-904f-45ebd08709ba": {
    "status": "ready",
    "stage": "done",
    "title": "mock_fir_constitution_itact.pdf",
    "total_chunks": 5,
    "ingested": 5,
    "percent": 100,
    "started_at": 1762203909.6317422,
    "updated_at": 1762203918.4043853,
    "eta_seconds": 0
  }
}